simsplitchem/__init__.py
simsplitchem/simsplitchem.py
simsplitchem/samplers/__init__.py
simsplitchem/utils/__init__.py
test/__init__.py
test/test_simsplitchem.py
SimplifySplittingChemicals-0.0.0.dist-info/LICENSE
SimplifySplittingChemicals-0.0.0.dist-info/METADATA
SimplifySplittingChemicals-0.0.0.dist-info/WHEEL
SimplifySplittingChemicals-0.0.0.dist-info/top_level.txt
SimplifySplittingChemicals-0.0.0.dist-info/RECORD
