Metadata-Version: 2.1
Name: SimplifySplittingChemicals
Version: 0.0.0
Summary: Simplifying ML Splitting with Chemicals
Home-page: https://github.com/JacksonBurns/SimplifySplittingChemicals
Author: Jackson Burns
Author-email: jburnsky@udel.edu
License: MIT
Platform: UNKNOWN
Classifier: Programming Language :: Python :: 3
License-File: LICENSE
